RubiDark/Device.py
RubiDark/WebAdress.py
RubiDark/__init__.py
RubiDark/clines_ph_web.py
RubiDark/copyright.py
RubiDark/encoder.py
RubiDark/rubika.py
RubiDark/send_server.py
RubiDark-2.0.0.dist-info/LICENCE
RubiDark-2.0.0.dist-info/METADATA
RubiDark-2.0.0.dist-info/WHEEL
RubiDark-2.0.0.dist-info/top_level.txt
RubiDark-2.0.0.dist-info/RECORD
